{"tags":"plant-based, fruits","co2-calculation":"wie EDB Zwetschgen","co2-value":0.36,"nutrition-id":"256","other-references":"","consistency":"körnig","combined-product":false,"co2-calculation-parameters":"","production-values":"S","id":1608,"references":"wie EDB Zwetschgen","production-names":"bio","calculation-process-documentation":"","origins":"Schweiz,Spanien,Niederlande","name":"Sauerkirschen","delete":false,"standard-origin":"Schweiz","conservation-values":"S, S, S","conservation-names":"tiefgekühlt, getrocknet, konserviert"}