{"tags":"animal-based, diary, beverage, milk","co2-value":2.24,"co2-calculation":"","nutrition-id":"M12A011","name-french":"lait acidulé","other-references":"","synonyms":"Dickmilch","combined-product":false,"co2-calculation-parameters":"","id":1665,"author":"EH","references":"TabelleZHAW: Kreuzer_2014_Treibhauspotenziale_Nahrungsmittel_eaternity_v2.0_EH; direkte Quelle: ZHAW Agrifood DB; soured milk, at dairy/kg/CH U","name-english":"curdled milk","calculation-process-documentation":"","name":"Sauermilch","delete":false}