{"tags":"sweet snack","co2-calculation":"value directly from reference (1)","co2-value":2.1,"nutrition-id":"831010","other-references":"","consistency":"fest","co2-calculation-parameters":"","combined-product":true,"production-values":"S","id":600,"references":"1. Büsser & Jungbluth, 2009. LCA of Chocolate Packed in Aluminium Foil Based Packaging. Page 2, text under figure 1. ","name-english":"chocolate (dark)","production-names":"bio","calculation-process-documentation":"","origins":"Schweiz,Spanien,Niederlande","name":"Schokolade","alternatives":"601,602","delete":false,"specification":"dunkel","standard-origin":"Schweiz"}