{"tags":"animal-based, diary","co2-calculation":"","co2-value":2.35,"nutrition-id":"821047","other-references":"","consistency":"zäh","combined-product":false,"co2-calculation-parameters":"","production-values":"S","id":820,"author":"EH","references":"TabelleZHAW: Kreuzer_2014_Treibhauspotenziale_Nahrungsmittel_eaternity_v2.0_EH; direkte Quelle: ZHAW Agrifood DB; curd, low- to semi-fat, at dairy/kg/CH U","name-english":"curd","production-names":"bio","calculation-process-documentation":"","origins":"Schweiz,Spanien,Niederlande","name":"Quark","delete":false,"specification":"mager","standard-origin":"Schweiz"}