{"nutr-vals":[{"unit":"g","component-id":"ALC","value":0},{"unit":"mg","component-id":"CA","value":295},{"unit":"g","component-id":"CHO","value":3.5},{"unit":"mg","component-id":"CHORL","value":57},{"unit":"mg","component-id":"CU","value":0.02},{"unit":"kcal","component-id":"ENERC","value":146},{"unit":"g","component-id":"FAMS","value":2.76},{"unit":"g","component-id":"FAPU","value":0.39},{"unit":"g","component-id":"FASAT","value":6.82},{"unit":"g","component-id":"FAT","value":10.9},{"unit":"mg","component-id":"FE","value":0.4},{"unit":"g","component-id":"FIBT","value":0},{"unit":"mg","component-id":"K","value":119},{"unit":"mg","component-id":"MG","value":17},{"unit":"mg","component-id":"NA","value":78},{"unit":"mg","component-id":"P","value":237},{"unit":"g","component-id":"PHYTAC","value":0},{"unit":"g","component-id":"PROT","value":8.8},{"unit":"ug","component-id":"SE","value":3.9},{"unit":"g","component-id":"STARCH","value":0},{"unit":"g","component-id":"SUGAR","value":3.5},{"unit":"RE","component-id":"VITA","value":128},{"unit":"mg","component-id":"VITC","value":0},{"unit":"mg","component-id":"VITE","value":0.21},{"unit":"g","component-id":"WATER","value":75.7},{"unit":"mg","component-id":"ZN","value":0.5}],"id":"166820","name":"CHEESE, RICOTTA, COW MILK","comment":"","country":"Italy"}