{"nutr-vals":[{"unit":"g","component-id":"ASH","value":1.1},{"unit":"mg","component-id":"CA","value":3},{"unit":"mg","component-id":"CHORL","value":95},{"unit":"g","component-id":"CHOT","value":0},{"unit":"mg","component-id":"CU","value":0.18},{"unit":"kcal","component-id":"ENERC","value":114},{"unit":"g","component-id":"FAMS","value":0.48},{"unit":"g","component-id":"FAPU","value":0.44},{"unit":"g","component-id":"FASAT","value":0.74},{"unit":"g","component-id":"FAT","value":2.03},{"unit":"mg","component-id":"FE","value":3.19},{"unit":"g","component-id":"FIBT","value":0},{"unit":"mg","component-id":"K","value":353},{"unit":"mg","component-id":"MG","value":27},{"unit":"mg","component-id":"MN","value":0.02},{"unit":"mg","component-id":"NA","value":51},{"unit":"mg","component-id":"P","value":188},{"unit":"g","component-id":"PROT","value":22.38},{"unit":"ug","component-id":"RETOL","value":0},{"unit":"mg","component-id":"RIBF","value":0.58},{"unit":"ug","component-id":"SE","value":9.7},{"unit":"mg","component-id":"THIA","value":0.32},{"unit":"RE","component-id":"VITA","value":0},{"unit":"mg","component-id":"VITC","value":0},{"unit":"g","component-id":"WATER","value":74.08},{"unit":"mg","component-id":"ZN","value":1.28}],"id":"17144","name":"Game meat, antelope, raw","comment":"","country":"USA"}